aimaster/__init__.py
aimaster/example.py
aimaster/nn.py
aimaster/nn1hlfb.py
aimaster/nn1hlhb.py
aimaster/nn1hlib.py
aimaster/nn1hlnb.py
aimaster/nn2hlfb.py
aimaster/nnfb.py
aimaster/nnmodel.py
aimaster/nnplotpipe.py
aimaster/nnplotq.py
aimaster/nnrelu.py
aimaster/nnsigmoid.py
aimaster/nntanh.py
aimaster/softmaxclassifier.py
aimaster/tools/__init__.py
aimaster/tools/nnplotter.py
aimaster-2.4.8.dist-info/LICENSE
aimaster-2.4.8.dist-info/METADATA
aimaster-2.4.8.dist-info/WHEEL
aimaster-2.4.8.dist-info/top_level.txt
aimaster-2.4.8.dist-info/RECORD
