Metadata-Version: 2.1
Name: aimaster
Version: 2.4.8
Summary: Artificial Neural Network learning tools
Home-page: https://github.com/kasinathps/aimaster
Author: Kasinath P.S
Author-email: kasinathps@gmail.com
License: MIT
Platform: UNKNOWN
Requires-Dist: numpy
Requires-Dist: scipy
Requires-Dist: matplotlib
